lofar_calculator/__init__.py
lofar_calculator/backend.py
lofar_calculator/calculator.py
lofar_calculator/generatepdf.py
lofar_calculator/gui.py
lofar_calculator/lotss_pointings.txt
lofar_calculator/requirements.txt
lofar_calculator/targetvis.py
lofar_calculator/static/__init__.py
lofar_calculator/static/summary_00114.pdf
lofar_calculator/static/summary_01073.pdf
lofar_calculator/static/summary_01083.pdf
lofar_calculator/static/summary_04980.pdf
lofar_calculator/static/summary_06695.pdf
lofar_calculator/static/summary_07638.pdf
lofar_calculator/static/summary_09208.pdf
lofar_calculator/static/summary_09836.pdf
lofar_calculator-0.1.1.dist-info/LICENSE.txt
lofar_calculator-0.1.1.dist-info/METADATA
lofar_calculator-0.1.1.dist-info/WHEEL
lofar_calculator-0.1.1.dist-info/top_level.txt
lofar_calculator-0.1.1.dist-info/RECORD
