Metadata-Version: 2.1
Name: lofar-calculator
Version: 0.1.1
Summary: The LOFAR Unified Calculator for Imaging, or LUCI, is a unified web interface that allows users to compute several parameters relevant for planning an interferometric observation with LOFAR.
Author-email: ASTRON <sdco@astron.nl>
Maintainer-email: "N. Peters" <peters@astron.nl>, "S. ter Veen" <veen@astron.nl>, "K. Kliffen" <kliffen@astron.nl>, "M. Altena" <altena@astron.nl>
License: 
Project-URL: Homepage, https://git.astron.nl/ao/sdco/LOFAR-calculator
Project-URL: Issues, https://git.astron.nl/ao/sdco/LOFAR-calculator/-/issues
Classifier: Programming Language :: Python :: 3
Classifier: License :: OSI Approved :: Apache Software License
Classifier: Operating System :: OS Independent
Classifier: Framework :: Dash
Classifier: Intended Audience :: Science/Research
Classifier: Topic :: Scientific/Engineering :: Astronomy
Requires-Python: >=3.8
License-File: LICENSE.txt
Requires-Dist: astroquery
Requires-Dist: astropy
Requires-Dist: dash
Requires-Dist: dash-bootstrap-components==0.13.1
Requires-Dist: ephem
Requires-Dist: fpdf2
Requires-Dist: matplotlib
Requires-Dist: numpy
Requires-Dist: kaleido
